ledpixelmath.cpython-35m-arm-linux-gnueabihf.so
ledpixelmath-1.0.3.dist-info/LICENSE
ledpixelmath-1.0.3.dist-info/METADATA
ledpixelmath-1.0.3.dist-info/WHEEL
ledpixelmath-1.0.3.dist-info/top_level.txt
ledpixelmath-1.0.3.dist-info/RECORD
